armada_sde_rest/__init__.py
armada_sde_rest/serializers.py
armada_sde_rest/settings.py
armada_sde_rest/urls.py
armada_sde_rest/views.py
armada_sde_rest/viewsets.py
armada_sde_rest/wsgi.py
armada_sde_rest/management/__init__.py
armada_sde_rest/management/commands/__init__.py
armada_sde_rest/management/commands/generate_viewsets.py
tests/migrations/__init__.py
tests/testapp/__init__.py
tests/testapp/admin.py
tests/testapp/apps.py
tests/testapp/models.py
tests/testapp/tests.py
tests/testapp/views.py
tests/testapp/migrations/__init__.py
armada_sde_rest-0.1.2.dist-info/LICENSE
armada_sde_rest-0.1.2.dist-info/METADATA
armada_sde_rest-0.1.2.dist-info/WHEEL
armada_sde_rest-0.1.2.dist-info/top_level.txt
armada_sde_rest-0.1.2.dist-info/RECORD
