Metadata-Version: 2.1
Name: armada-sde-rest
Version: 0.1.2
Summary: A pluggable Django app with ReST endpoints for the SDE
Home-page: https://github.com/kriberg/armada-sde.git
Author: Kristian Berg
Author-email: eve.vittoros@gmail.com
License: LGPLv3
Platform: UNKNOWN
Classifier: License :: OSI Approved :: GNU Lesser General Public License v3 (LGPLv3)
Classifier: Development Status :: 4 - Beta
Classifier: Programming Language :: Python
Classifier: Programming Language :: Python :: 3
Classifier: Programming Language :: Python :: 3.6
Classifier: Programming Language :: Python :: Implementation :: CPython
Classifier: Topic :: Games/Entertainment
Requires-Python: >=3.5.0
Requires-Dist: Django
Requires-Dist: autopep8
Requires-Dist: djangorestframework
Requires-Dist: armada-sde
